{"files":{"apps/worker/dist/trigger/index.js.map":{"size":211,"mtime_nanos":1780397750906022545,"mode":420,"is_dir":false},"apps/worker/dist/bootstrap/index.d.ts.map":{"size":278,"mtime_nanos":1780397750903190038,"mode":420,"is_dir":false},"apps/worker/dist/bootstrap":{"size":0,"mtime_nanos":0,"mode":0,"is_dir":true},"apps/worker/dist/trigger/index.js":{"size":166,"mtime_nanos":1780397750906236420,"mode":420,"is_dir":false},"apps/worker/dist/trigger/jobs/index.d.ts.map":{"size":176,"mtime_nanos":1780397750905070167,"mode":420,"is_dir":false},"apps/worker/dist/trigger/jobs/event-bridge.d.ts":{"size":1058,"mtime_nanos":1780397750888121086,"mode":420,"is_dir":false},"apps/worker/dist/trigger/registry/index.d.ts.map":{"size":432,"mtime_nanos":1780397750899420571,"mode":420,"is_dir":false},"apps/worker/dist/index.js.map":{"size":261,"mtime_nanos":1780397750909003927,"mode":420,"is_dir":false},"apps/worker/dist/trigger/jobs/index.js":{"size":105,"mtime_nanos":1780397750904593416,"mode":420,"is_dir":false},"apps/worker/.turbo/turbo-build.log":{"size":71,"mtime_nanos":1780397924927476196,"mode":420,"is_dir":false},"apps/worker/dist/trigger/jobs/index.d.ts":{"size":107,"mtime_nanos":1780397750905265168,"mode":420,"is_dir":false},"apps/worker/dist/bootstrap/index.js":{"size":934,"mtime_nanos":1780397750902017869,"mode":420,"is_dir":false},"apps/worker/dist/trigger/jobs/event-bridge.d.ts.map":{"size":385,"mtime_nanos":1780397760905057732,"mode":420,"is_dir":false},"apps/worker/dist/trigger/registry/index.d.ts":{"size":882,"mtime_nanos":1780397750899868989,"mode":420,"is_dir":false},"apps/worker/dist/trigger/jobs/event-bridge.js.map":{"size":830,"mtime_nanos":1780397760902502809,"mode":420,"is_dir":false},"apps/worker/dist/bootstrap/index.js.map":{"size":490,"mtime_nanos":1780397750901730743,"mode":420,"is_dir":false},"apps/worker/dist/index.js":{"size":285,"mtime_nanos":1780397750909166677,"mode":420,"is_dir":false},"apps/worker/dist/index.d.ts":{"size":287,"mtime_nanos":1780397750909689303,"mode":420,"is_dir":false},"apps/worker/dist":{"size":0,"mtime_nanos":0,"mode":0,"is_dir":true},"apps/worker/dist/trigger/jobs":{"size":0,"mtime_nanos":0,"mode":0,"is_dir":true},"apps/worker/dist/bootstrap/index.d.ts":{"size":590,"mtime_nanos":1780397750903447955,"mode":420,"is_dir":false},"apps/worker/dist/trigger/registry/index.js.map":{"size":1683,"mtime_nanos":1780397750896478647,"mode":420,"is_dir":false},"apps/worker/dist/trigger/index.d.ts":{"size":168,"mtime_nanos":1780397750908327967,"mode":420,"is_dir":false},"apps/worker/dist/trigger/jobs/event-bridge.js":{"size":1463,"mtime_nanos":1780397760902758684,"mode":420,"is_dir":false},"apps/worker/dist/trigger":{"size":0,"mtime_nanos":0,"mode":0,"is_dir":true},"apps/worker/dist/trigger/registry":{"size":0,"mtime_nanos":0,"mode":0,"is_dir":true},"apps/worker/dist/trigger/registry/index.js":{"size":2322,"mtime_nanos":1780397750896916856,"mode":420,"is_dir":false},"apps/worker/dist/index.d.ts.map":{"size":263,"mtime_nanos":1780397750909534720,"mode":420,"is_dir":false},"apps/worker/dist/trigger/index.d.ts.map":{"size":213,"mtime_nanos":1780397750908058133,"mode":420,"is_dir":false},"apps/worker/dist/trigger/jobs/index.js.map":{"size":174,"mtime_nanos":1780397750904436583,"mode":420,"is_dir":false}},"order":["apps/worker/.turbo/turbo-build.log","apps/worker/dist","apps/worker/dist/bootstrap","apps/worker/dist/bootstrap/index.d.ts","apps/worker/dist/bootstrap/index.d.ts.map","apps/worker/dist/bootstrap/index.js","apps/worker/dist/bootstrap/index.js.map","apps/worker/dist/index.d.ts","apps/worker/dist/index.d.ts.map","apps/worker/dist/index.js","apps/worker/dist/index.js.map","apps/worker/dist/trigger","apps/worker/dist/trigger/index.d.ts","apps/worker/dist/trigger/index.d.ts.map","apps/worker/dist/trigger/index.js","apps/worker/dist/trigger/index.js.map","apps/worker/dist/trigger/jobs","apps/worker/dist/trigger/jobs/event-bridge.d.ts","apps/worker/dist/trigger/jobs/event-bridge.d.ts.map","apps/worker/dist/trigger/jobs/event-bridge.js","apps/worker/dist/trigger/jobs/event-bridge.js.map","apps/worker/dist/trigger/jobs/index.d.ts","apps/worker/dist/trigger/jobs/index.d.ts.map","apps/worker/dist/trigger/jobs/index.js","apps/worker/dist/trigger/jobs/index.js.map","apps/worker/dist/trigger/registry","apps/worker/dist/trigger/registry/index.d.ts","apps/worker/dist/trigger/registry/index.d.ts.map","apps/worker/dist/trigger/registry/index.js","apps/worker/dist/trigger/registry/index.js.map"]}